Metadata-Version: 2.1
Name: retailapi-utils
Version: 0.2
Summary: RetailCRM API utility library
Home-page: https://github.com/MirrSs/retailcrm-api-utils
Author: Ilya Charauko
Author-email: ilyacharauko@gmail.com
